wff/__init__.py
wff/wff.py
wff-0.0.0.1.dist-info/LICENSE
wff-0.0.0.1.dist-info/METADATA
wff-0.0.0.1.dist-info/WHEEL
wff-0.0.0.1.dist-info/top_level.txt
wff-0.0.0.1.dist-info/RECORD
