Metadata-Version: 2.1
Name: wff
Version: 0.0.0.1
Summary: Python library for building and working with propositional formulas.
Home-page: https://github.com/reity/wff
Author: Andrei Lapets
Author-email: a@lapets.io
License: MIT
Platform: UNKNOWN
